cryptorandom/__init__.py
cryptorandom/cryptorandom.py
cryptorandom/sample.py
cryptorandom/tests/__init__.py
cryptorandom/tests/test_cryptorandom.py
cryptorandom/tests/test_sample.py
cryptorandom-0.4.dist-info/licenses/LICENSE
cryptorandom-0.4.dist-info/METADATA
cryptorandom-0.4.dist-info/WHEEL
cryptorandom-0.4.dist-info/top_level.txt
cryptorandom-0.4.dist-info/RECORD
