Metadata-Version: 2.4
Name: cryptorandom
Version: 0.4
Summary: Pseudorandom number generator and random sampling using cryptographic hash functions
Home-page: http://www.github.com/statlab/cryptorandom
Download-URL: http://www.github.com/statlab/cryptorandom
Author: Amanda Glazer, Kellie Ottoboni, Philip B. Stark
Author-email: pbstark@berkeley.edu
License: BSD License
Classifier: Development Status :: 4 - Beta
Classifier: Environment :: Console
Classifier: Intended Audience :: Developers
Classifier: Intended Audience :: Science/Research
Classifier: License :: OSI Approved :: BSD License
Classifier: Programming Language :: Python
Classifier: Programming Language :: Python :: 3.11
Classifier: Programming Language :: Python :: 3.12
Classifier: Programming Language :: Python :: 3.13
Classifier: Topic :: Scientific/Engineering
Classifier: Operating System :: Microsoft :: Windows
Classifier: Operating System :: POSIX
Classifier: Operating System :: Unix
Classifier: Operating System :: MacOS
License-File: LICENSE
Requires-Dist: numpy>=2.0
Requires-Dist: scipy>=1.12
Dynamic: author
Dynamic: author-email
Dynamic: classifier
Dynamic: description
Dynamic: download-url
Dynamic: home-page
Dynamic: license
Dynamic: license-file
Dynamic: requires-dist
Dynamic: summary
